<database>
  <name>massive</name>
  <description>The Massive Database contains information about all the proteomics/metabolomics datasets in massive</description>
  <release>1.0</release>
  <release_date>15-11-10</release_date>
  <entry_count>1</entry_count>
  <entries>
    <entry id="MSV000078508">
      <name>Proteogenomic analysis of colorectal tumor cells</name>
      <description>We performed proteogenomic analysis on a panel of 10 colorectal carcinoma cell lines with differences in DNA mismatch repair status (PMID:24247723).</description>
      <cross_references/>
      <dates>
        <date type="submission" value="13-12-10"/>
      </dates>
      <additional_fields>
        <field name="omics_type">Proteomics</field>
        <field name="full_dataset_link">http://massive.ucsd.edu/ProteoSAFe/result.jsp?task=7b16bd83b5254e348c75cd6e330a5144&amp;view=advanced_view</field>
        <field name="repository">massive</field>
        <field name="instrument_platform">Not available</field>
        <field name="modification">Not available</field>
        <field name="technology_type">Not available</field>
        <field name="submitter">null</field>
      </additional_fields>
    </entry>
  </entries>
</database>
